thira/__init__.py
thira/binary.py
thira/cli.py
thira/hooks.py
thira/installer.py
thira/setup.py
thira/uninstaller.py
thira-1.30.0.dist-info/METADATA
thira-1.30.0.dist-info/WHEEL
thira-1.30.0.dist-info/entry_points.txt
thira-1.30.0.dist-info/RECORD
