Metadata-Version: 2.3
Name: thira
Version: 1.30.0
Summary: A Git hooks manager and commit message linter
Keywords: git,hooks,commit,lint,cli
Author: Your Name
Author-email: your.email@example.com
Requires-Python: >=3.7,<4.0
Classifier: Programming Language :: Python :: 3
Classifier: Programming Language :: Python :: 3.7
Classifier: Programming Language :: Python :: 3.8
Classifier: Programming Language :: Python :: 3.9
Classifier: Programming Language :: Python :: 3.10
Classifier: Programming Language :: Python :: 3.11
Classifier: Programming Language :: Python :: 3.12
Classifier: Programming Language :: Python :: 3.13
Requires-Dist: pathlib (>=1.0.1,<2.0.0)
Requires-Dist: requests (>=2.31.0,<3.0.0)
Project-URL: Documentation, https://github.com/ervan0707/thira#readme
Project-URL: Homepage, https://github.com/ervan0707/thira
Project-URL: Repository, https://github.com/ervan0707/thira
